{
  "$schema": "https://pptx.dev/schema/opf-layout/v1",
  "id": "chart-3x-right-title-center",
  "name": "Chart_3x_Right_Title_Center",
  "label": "Chart 3x Right Title Center",
  "contentAlignment": "Center",
  "contentBox": false,
  "contentMultiple": "3x",
  "contentTypeChartPrimary": "Right",
  "contentTypeImageFill": "None",
  "contentTypeListBullet": "None",
  "contentTypeListHeading": false,
  "contentType": "Chart",
  "groupDefault": false,
  "groupHash": "ca297036b52409e1379fa1b912d965c7f5a134470788ab86a1203994d0601dcf",
  "master": "Dark",
  "masterSlideIndex": 168,
  "slideImage": false,
  "slideImageAlignment": "None",
  "slideLayoutDirection": "Horizontal",
  "slideTitle": true,
  "slideTitleAlignment": "Center"
}
