{
  "$schema": "https://pptx.dev/schema/opf-layout/v1",
  "id": "text-1x-left-box",
  "name": "Text_1x_Left_Box",
  "label": "Text 1x Left Box",
  "contentAlignment": "Left",
  "contentBox": true,
  "contentMultiple": "1x",
  "contentTypeChartPrimary": "None",
  "contentTypeImageFill": "None",
  "contentTypeListBullet": "None",
  "contentTypeListHeading": false,
  "contentType": "Text",
  "groupDefault": false,
  "groupHash": "0d30d7585104e84cd3dfe510558279182dc32b193d35015cda0aff256a11de5d",
  "master": "Dark",
  "masterSlideIndex": 16,
  "slideImage": false,
  "slideImageAlignment": "None",
  "slideLayoutDirection": "Horizontal",
  "slideTitle": false,
  "slideTitleAlignment": "None"
}
